calculator_sdk/__init__.py
calculator_sdk/aithmatic.py
calculator_sdk/calculator.py
calculator_sdk-0.1.4.dist-info/METADATA
calculator_sdk-0.1.4.dist-info/WHEEL
calculator_sdk-0.1.4.dist-info/top_level.txt
calculator_sdk-0.1.4.dist-info/RECORD
