Metadata-Version: 2.1
Name: calculator_sdk
Version: 0.1.4
Summary: A simple calculator SDK
Requires-Dist: py4j
